pycocoa/LICENSE
pycocoa/__init__.py
pycocoa/__main__.py
pycocoa/apps.py
pycocoa/bases.py
pycocoa/colors.py
pycocoa/deprecated.py
pycocoa/dicts.py
pycocoa/faults.py
pycocoa/fonts.py
pycocoa/geometry.py
pycocoa/getters.py
pycocoa/internals.py
pycocoa/lazily.py
pycocoa/lists.py
pycocoa/menus.py
pycocoa/nstypes.py
pycocoa/octypes.py
pycocoa/oslibs.py
pycocoa/panels.py
pycocoa/printers.py
pycocoa/pytypes.py
pycocoa/runtime.py
pycocoa/screens.py
pycocoa/sets.py
pycocoa/strs.py
pycocoa/tables.py
pycocoa/tuples.py
pycocoa/utils.py
pycocoa/windows.py
pycocoa-25.3.25.dist-info/METADATA
pycocoa-25.3.25.dist-info/WHEEL
pycocoa-25.3.25.dist-info/top_level.txt
pycocoa-25.3.25.dist-info/RECORD
