Metadata-Version: 2.1
Name: pycocoa
Version: 25.3.25
Summary: Basic Python binding to macOS' Objective-C Cocoa
Home-page: https://GitHub.com/mrJean1/PyCocoa
Author: Jean M. Brouwers
Author-email: mrJean1@Gmail.com
Maintainer: Jean M. Brouwers
Maintainer-email: mrJean1@Gmail.com
License: MIT
Keywords: Apple-Si Apple-Silicon Cocoa cocoa-python cocoavlc ctypes fault faults faulthandler macOS MacOSX Obj-C Objective-C pycocoa Python-VLC segfaulty transparent VLC VLCplayer
Classifier: Development Status :: 4 - Beta
Classifier: Environment :: MacOS X :: Cocoa
Classifier: Intended Audience :: Developers
Classifier: License :: OSI Approved :: BSD License
Classifier: License :: OSI Approved :: MIT License
Classifier: Operating System :: MacOS :: MacOS X
Classifier: Programming Language :: Python
Classifier: Programming Language :: Python :: 2.7
Classifier: Programming Language :: Python :: 3.9
Classifier: Programming Language :: Python :: 3.10
Classifier: Programming Language :: Python :: 3.11
Classifier: Programming Language :: Python :: 3.12
Classifier: Programming Language :: Python :: 3.13
Classifier: Topic :: Software Development
Classifier: Topic :: Software Development :: User Interfaces
Classifier: Topic :: Scientific/Engineering :: Human Machine Interfaces
